sinatra_pro/RATE.py
sinatra_pro/__init__.py
sinatra_pro/__main__.py
sinatra_pro/check_version.py
sinatra_pro/directions.py
sinatra_pro/euler.py
sinatra_pro/gp.py
sinatra_pro/mesh.py
sinatra_pro/reconstruction.py
sinatra_pro/traj_reader.py
SINATRA_Pro-0.0.1.dist-info/METADATA
SINATRA_Pro-0.0.1.dist-info/WHEEL
SINATRA_Pro-0.0.1.dist-info/top_level.txt
SINATRA_Pro-0.0.1.dist-info/RECORD
