Metadata-Version: 2.1
Name: SINATRA-Pro
Version: 0.0.1
Summary: Python3 package for SINATRA Pro.
Home-page: https://github.com/lcrawlab/SINATRA-Pro
Author: Wai Shing Tang
License: MIT License
Project-URL: Bug Tracker, https://github.com/lcrawlab/SINATRA-Pro/issues
Platform: UNKNOWN
Classifier: Programming Language :: Python :: 3
Classifier: License :: OSI Approved :: MIT License
Classifier: Operating System :: OS Independent
Requires-Python: >=3.6
Requires-Dist: numpy (>=1.18.0)
Requires-Dist: scipy (>=1.5.0)
Requires-Dist: MDAnalysis (>=0.20.0)
Requires-Dist: fast-histogram (>=0.9)
Requires-Dist: joblib (>=0.16.0)
